pysie_accounting/__init__.py
pysie_accounting/pysie.py
test/__init__.py
test/test_sie.py
pysie_accounting-0.0.2.dist-info/METADATA
pysie_accounting-0.0.2.dist-info/WHEEL
pysie_accounting-0.0.2.dist-info/top_level.txt
pysie_accounting-0.0.2.dist-info/RECORD
