Metadata-Version: 2.1
Name: pysie_accounting
Version: 0.0.2
Summary: SIE file decoder
Home-page: https://github.com/thpe/pysie-accounting
Author: Thomas Petig
Author-email: thomas@petig.eu
Classifier: Programming Language :: Python :: 3
Classifier: License :: OSI Approved :: MIT License
Classifier: Operating System :: OS Independent
